{
    "banner": " div.header.content > a.logo",
    "hotSeller":"div.content-heading:nth-child(2)",
    "gear": "#ui-id-6",
    "search": "#search",
    "navigation": "#ui-id-2",
    "fitness": "#ui-id-26",
    "allProducts": "ol.products.list.items.product-items li",
    "secondProduct": "ol li.item.product.product-item:nth-child(2)",
    "productPrice": "span.price-container.tax.weee span.price-wrapper > span.price",
    "productName": "strong.product.name.product-item-name > a.product-item-link",
    "addToCart": "li.item.product.product-item:nth-child(2) > div.product-item-info",
    "quantity": "div.control.qty > input.input-text.qty",
    "addCartBtn": "#product-addtocart-button",
    "cartIcon": "header.page-header div.header.content > div.minicart-wrapper",
    "cartDesc":"header.page-header div.header.content > div.minicart-wrapper",
    "itemsId": "#ui-id-1",
    "totalItems":"div.items-total:nth-child(2) > span.count:nth-child(1)",
    "totalAmount": "div.amount.price-container span.price-wrapper > span.price",
    "checkoutBtn":"#top-cart-btn-checkout",
    "shippingField" : "div.field.required > div.control._with-tooltip",
    "shippingEmail": "input#customer-email",
    "toPayment":"div.primary > button.button.action.continue.primary",
    "shippingFee": "tr.row td.col.col-method:nth-child(1) > input.radio",
    "prodSummaryId": "div#opc-sidebar",
    "prodPrice": "td.amount>strong>span.price",
    "orderSuccess": "div.payment-method-billing-address > div.checkout-billing-address",
    "orderButton": "button[title='Place Order']",
    "shoppingBtn": "a.continue[href='https://magento.softwaretestingboard.com/']"
}